<annotation>
	<folder>enfermas</folder>
	<filename>9img28.jpg</filename>
	<path>/home/jcaceres/Documentos/Compartido/UNIR/TFM/GITHUB/Imagenes/enfermas/9img28.jpg</path>
	<source>
		<database>Unknown</database>
	</source>
	<size>
		<width>3280</width>
		<height>2464</height>
		<depth>3</depth>
	</size>
	<segmented>0</segmented>
	<object>
		<name>TIZON</name>
		<pose>Unspecified</pose>
		<truncated>0</truncated>
		<difficult>0</difficult>
		<bndbox>
			<xmin>1468</xmin>
			<ymin>73</ymin>
			<xmax>1881</xmax>
			<ymax>1257</ymax>
		</bndbox>
	</object>
	<object>
		<name>TIZON</name>
		<pose>Unspecified</pose>
		<truncated>0</truncated>
		<difficult>0</difficult>
		<bndbox>
			<xmin>1501</xmin>
			<ymin>1378</ymin>
			<xmax>1807</xmax>
			<ymax>1960</ymax>
		</bndbox>
	</object>
	<object>
		<name>TIZON</name>
		<pose>Unspecified</pose>
		<truncated>0</truncated>
		<difficult>0</difficult>
		<bndbox>
			<xmin>1866</xmin>
			<ymin>1996</ymin>
			<xmax>2107</xmax>
			<ymax>2260</ymax>
		</bndbox>
	</object>
	<object>
		<name>TIZON</name>
		<pose>Unspecified</pose>
		<truncated>0</truncated>
		<difficult>0</difficult>
		<bndbox>
			<xmin>1960</xmin>
			<ymin>24</ymin>
			<xmax>2355</xmax>
			<ymax>1178</ymax>
		</bndbox>
	</object>
	<object>
		<name>TIZON</name>
		<pose>Unspecified</pose>
		<truncated>0</truncated>
		<difficult>0</difficult>
		<bndbox>
			<xmin>1940</xmin>
			<ymin>1211</ymin>
			<xmax>2219</xmax>
			<ymax>1637</ymax>
		</bndbox>
	</object>
	<object>
		<name>TIZON</name>
		<pose>Unspecified</pose>
		<truncated>0</truncated>
		<difficult>0</difficult>
		<bndbox>
			<xmin>2596</xmin>
			<ymin>1109</ymin>
			<xmax>2860</xmax>
			<ymax>1506</ymax>
		</bndbox>
	</object>
	<object>
		<name>STEWART</name>
		<pose>Unspecified</pose>
		<truncated>0</truncated>
		<difficult>0</difficult>
		<bndbox>
			<xmin>778</xmin>
			<ymin>670</ymin>
			<xmax>1037</xmax>
			<ymax>988</ymax>
		</bndbox>
	</object>
	<object>
		<name>STEWART</name>
		<pose>Unspecified</pose>
		<truncated>0</truncated>
		<difficult>0</difficult>
		<bndbox>
			<xmin>688</xmin>
			<ymin>297</ymin>
			<xmax>798</xmax>
			<ymax>455</ymax>
		</bndbox>
	</object>
</annotation>
