<annotation>
	<folder>enfermas</folder>
	<filename>9img21.jpg</filename>
	<path>/home/jcaceres/Documentos/Compartido/UNIR/TFM/GITHUB/Imagenes/enfermas/9img21.jpg</path>
	<source>
		<database>Unknown</database>
	</source>
	<size>
		<width>3280</width>
		<height>2464</height>
		<depth>3</depth>
	</size>
	<segmented>0</segmented>
	<object>
		<name>TIZON</name>
		<pose>Unspecified</pose>
		<truncated>1</truncated>
		<difficult>0</difficult>
		<bndbox>
			<xmin>1</xmin>
			<ymin>57</ymin>
			<xmax>717</xmax>
			<ymax>888</ymax>
		</bndbox>
	</object>
	<object>
		<name>TIZON</name>
		<pose>Unspecified</pose>
		<truncated>1</truncated>
		<difficult>0</difficult>
		<bndbox>
			<xmin>1</xmin>
			<ymin>1101</ymin>
			<xmax>830</xmax>
			<ymax>2044</ymax>
		</bndbox>
	</object>
	<object>
		<name>TIZON</name>
		<pose>Unspecified</pose>
		<truncated>1</truncated>
		<difficult>0</difficult>
		<bndbox>
			<xmin>19</xmin>
			<ymin>2114</ymin>
			<xmax>784</xmax>
			<ymax>2464</ymax>
		</bndbox>
	</object>
	<object>
		<name>TIZON</name>
		<pose>Unspecified</pose>
		<truncated>0</truncated>
		<difficult>0</difficult>
		<bndbox>
			<xmin>814</xmin>
			<ymin>2050</ymin>
			<xmax>1060</xmax>
			<ymax>2278</ymax>
		</bndbox>
	</object>
	<object>
		<name>TIZON</name>
		<pose>Unspecified</pose>
		<truncated>0</truncated>
		<difficult>0</difficult>
		<bndbox>
			<xmin>1601</xmin>
			<ymin>506</ymin>
			<xmax>2148</xmax>
			<ymax>1657</ymax>
		</bndbox>
	</object>
	<object>
		<name>TIZON</name>
		<pose>Unspecified</pose>
		<truncated>0</truncated>
		<difficult>0</difficult>
		<bndbox>
			<xmin>2245</xmin>
			<ymin>498</ymin>
			<xmax>2543</xmax>
			<ymax>878</ymax>
		</bndbox>
	</object>
	<object>
		<name>TIZON</name>
		<pose>Unspecified</pose>
		<truncated>0</truncated>
		<difficult>0</difficult>
		<bndbox>
			<xmin>2225</xmin>
			<ymin>911</ymin>
			<xmax>2748</xmax>
			<ymax>1642</ymax>
		</bndbox>
	</object>
	<object>
		<name>TIZON</name>
		<pose>Unspecified</pose>
		<truncated>1</truncated>
		<difficult>0</difficult>
		<bndbox>
			<xmin>2248</xmin>
			<ymin>1732</ymin>
			<xmax>2781</xmax>
			<ymax>2464</ymax>
		</bndbox>
	</object>
	<object>
		<name>TIZON</name>
		<pose>Unspecified</pose>
		<truncated>0</truncated>
		<difficult>0</difficult>
		<bndbox>
			<xmin>1668</xmin>
			<ymin>1667</ymin>
			<xmax>2101</xmax>
			<ymax>2439</ymax>
		</bndbox>
	</object>
</annotation>
